{
    "TIPO": "SIS",
    "NOMBRE": "REVS2",
    "IDENTIFICADOR": 1,
    "LECTURAS": [
        {
            "FECHA": "2025-08-13",
            "TIEMPO": "12:00:00",
            "LATITUD": -0.212076,
            "LONGITUD": -78.491481,
            "ALTURA": 2803.4,
            "PASA_BANDA": "0012",
            "PASA_BAJO": "0009",
            "PASA_ALTO": "0051",
            "BATERIA": 12.46
        },
        {
            "FECHA": "2025-08-13",
            "TIEMPO": "12:01:00",
            "LATITUD": -0.212078,
            "LONGITUD": -78.491469,
            "ALTURA": 2807.5,
            "PASA_BANDA": "0015",
            "PASA_BAJO": "0019",
            "PASA_ALTO": "0056",
            "BATERIA": 12.46
        },
        {
            "FECHA": "2025-08-13",
            "TIEMPO": "12:02:00",
            "LATITUD": -0.212085,
            "LONGITUD": -78.491459,
            "ALTURA": 2811.5,
            "PASA_BANDA": "0012",
            "PASA_BAJO": "0020",
            "PASA_ALTO": "0053",
            "BATERIA": 12.46
        },
        {
            "FECHA": "2025-08-13",
            "TIEMPO": "12:03:00",
            "LATITUD": -0.212085,
            "LONGITUD": -78.491459,
            "ALTURA": 2811.8,
            "PASA_BANDA": "0012",
            "PASA_BAJO": "0010",
            "PASA_ALTO": "0051",
            "BATERIA": 12.47
        },
        {
            "FECHA": "2025-08-13",
            "TIEMPO": "12:04:00",
            "LATITUD": -0.212067,
            "LONGITUD": -78.491456,
            "ALTURA": 2820.4,
            "PASA_BANDA": "0008",
            "PASA_BAJO": "0013",
            "PASA_ALTO": "0056",
            "BATERIA": 12.46
        },
        {
            "FECHA": "2025-08-13",
            "TIEMPO": "12:05:00",
            "LATITUD": -0.212061,
            "LONGITUD": -78.491472,
            "ALTURA": 2801.0,
            "PASA_BANDA": "0016",
            "PASA_BAJO": "0014",
            "PASA_ALTO": "0051",
            "BATERIA": 12.47
        },
        {
            "FECHA": "2025-08-13",
            "TIEMPO": "12:06:00",
            "LATITUD": -0.21207,
            "LONGITUD": -78.491454,
            "ALTURA": 2818.0,
            "PASA_BANDA": "0012",
            "PASA_BAJO": "0015",
            "PASA_ALTO": "0053",
            "BATERIA": 12.46
        },
        {
            "FECHA": "2025-08-13",
            "TIEMPO": "12:07:00",
            "LATITUD": -0.212052,
            "LONGITUD": -78.491471,
            "ALTURA": 2794.2,
            "PASA_BANDA": "0015",
            "PASA_BAJO": "0011",
            "PASA_ALTO": "0055",
            "BATERIA": 12.47
        },
        {
            "FECHA": "2025-08-13",
            "TIEMPO": "12:08:00",
            "LATITUD": -0.212068,
            "LONGITUD": -78.491482,
            "ALTURA": 2786.1,
            "PASA_BANDA": "0016",
            "PASA_BAJO": "0014",
            "PASA_ALTO": "0051",
            "BATERIA": 12.46
        },
        {
            "FECHA": "2025-08-13",
            "TIEMPO": "12:09:00",
            "LATITUD": -0.212069,
            "LONGITUD": -78.491496,
            "ALTURA": 2785.8,
            "PASA_BANDA": "0015",
            "PASA_BAJO": "0013",
            "PASA_ALTO": "0055",
            "BATERIA": 12.47
        },
        {
            "FECHA": "2025-08-13",
            "TIEMPO": "12:10:00",
            "LATITUD": -0.212064,
            "LONGITUD": -78.491492,
            "ALTURA": 2789.9,
            "PASA_BANDA": "0011",
            "PASA_BAJO": "0010",
            "PASA_ALTO": "0053",
            "BATERIA": 12.46
        },
        {
            "FECHA": "2025-08-13",
            "TIEMPO": "12:11:00",
            "LATITUD": -0.212063,
            "LONGITUD": -78.491473,
            "ALTURA": 2790.6,
            "PASA_BANDA": "0009",
            "PASA_BAJO": "0012",
            "PASA_ALTO": "0056",
            "BATERIA": 12.47
        },
        {
            "FECHA": "2025-08-13",
            "TIEMPO": "12:12:00",
            "LATITUD": -0.212146,
            "LONGITUD": -78.491468,
            "ALTURA": 2767.7,
            "PASA_BANDA": "0014",
            "PASA_BAJO": "0024",
            "PASA_ALTO": "0053",
            "BATERIA": 12.46
        },
        {
            "FECHA": "2025-08-13",
            "TIEMPO": "12:13:00",
            "LATITUD": -0.212131,
            "LONGITUD": -78.491454,
            "ALTURA": 2791.4,
            "PASA_BANDA": "0008",
            "PASA_BAJO": "0019",
            "PASA_ALTO": "0053",
            "BATERIA": 12.47
        },
        {
            "FECHA": "2025-08-13",
            "TIEMPO": "12:14:00",
            "LATITUD": -0.212093,
            "LONGITUD": -78.491419,
            "ALTURA": 2822.0,
            "PASA_BANDA": "0015",
            "PASA_BAJO": "0017",
            "PASA_ALTO": "0051",
            "BATERIA": 12.46
        },
        {
            "FECHA": "2025-08-13",
            "TIEMPO": "12:15:00",
            "LATITUD": -0.212093,
            "LONGITUD": -78.491443,
            "ALTURA": 2813.0,
            "PASA_BANDA": "0012",
            "PASA_BAJO": "0011",
            "PASA_ALTO": "0055",
            "BATERIA": 12.47
        },
        {
            "FECHA": "2025-08-13",
            "TIEMPO": "12:16:00",
            "LATITUD": -0.212118,
            "LONGITUD": -78.491402,
            "ALTURA": 2818.0,
            "PASA_BANDA": "0011",
            "PASA_BAJO": "0009",
            "PASA_ALTO": "0056",
            "BATERIA": 12.47
        },
        {
            "FECHA": "2025-08-13",
            "TIEMPO": "12:17:00",
            "LATITUD": -0.212121,
            "LONGITUD": -78.491404,
            "ALTURA": 2814.3,
            "PASA_BANDA": "0009",
            "PASA_BAJO": "0009",
            "PASA_ALTO": "0053",
            "BATERIA": 12.47
        },
        {
            "FECHA": "2025-08-13",
            "TIEMPO": "12:18:00",
            "LATITUD": -0.212068,
            "LONGITUD": -78.491395,
            "ALTURA": 2844.3,
            "PASA_BANDA": "0008",
            "PASA_BAJO": "0012",
            "PASA_ALTO": "0053",
            "BATERIA": 12.46
        },
        {
            "FECHA": "2025-08-13",
            "TIEMPO": "12:19:00",
            "LATITUD": -0.212088,
            "LONGITUD": -78.491454,
            "ALTURA": 2815.5,
            "PASA_BANDA": "0015",
            "PASA_BAJO": "0010",
            "PASA_ALTO": "0051",
            "BATERIA": 12.46
        },
        {
            "FECHA": "2025-08-13",
            "TIEMPO": "12:20:00",
            "LATITUD": -0.212139,
            "LONGITUD": -78.491465,
            "ALTURA": 2794.3,
            "PASA_BANDA": "0012",
            "PASA_BAJO": "0009",
            "PASA_ALTO": "0051",
            "BATERIA": 12.46
        },
        {
            "FECHA": "2025-08-13",
            "TIEMPO": "12:21:00",
            "LATITUD": -0.212155,
            "LONGITUD": -78.491489,
            "ALTURA": 2784.7,
            "PASA_BANDA": "0011",
            "PASA_BAJO": "0008",
            "PASA_ALTO": "0056",
            "BATERIA": 12.47
        },
        {
            "FECHA": "2025-08-13",
            "TIEMPO": "12:22:00",
            "LATITUD": -0.212122,
            "LONGITUD": -78.491471,
            "ALTURA": 2798.3,
            "PASA_BANDA": "0009",
            "PASA_BAJO": "0010",
            "PASA_ALTO": "0056",
            "BATERIA": 12.46
        },
        {
            "FECHA": "2025-08-13",
            "TIEMPO": "12:23:00",
            "LATITUD": -0.212103,
            "LONGITUD": -78.491471,
            "ALTURA": 2810.4,
            "PASA_BANDA": "0015",
            "PASA_BAJO": "0013",
            "PASA_ALTO": "0053",
            "BATERIA": 12.47
        },
        {
            "FECHA": "2025-08-13",
            "TIEMPO": "12:24:00",
            "LATITUD": -0.212094,
            "LONGITUD": -78.491471,
            "ALTURA": 2811.9,
            "PASA_BANDA": "0008",
            "PASA_BAJO": "0019",
            "PASA_ALTO": "0053",
            "BATERIA": 12.46
        },
        {
            "FECHA": "2025-08-13",
            "TIEMPO": "12:25:00",
            "LATITUD": -0.21208,
            "LONGITUD": -78.491455,
            "ALTURA": 2833.1,
            "PASA_BANDA": "0016",
            "PASA_BAJO": "0011",
            "PASA_ALTO": "0051",
            "BATERIA": 12.46
        },
        {
            "FECHA": "2025-08-13",
            "TIEMPO": "12:26:00",
            "LATITUD": -0.212082,
            "LONGITUD": -78.491447,
            "ALTURA": 2828.8,
            "PASA_BANDA": "0015",
            "PASA_BAJO": "0022",
            "PASA_ALTO": "0051",
            "BATERIA": 12.46
        },
        {
            "FECHA": "2025-08-13",
            "TIEMPO": "12:27:00",
            "LATITUD": -0.212142,
            "LONGITUD": -78.491443,
            "ALTURA": 2831.0,
            "PASA_BANDA": "0011",
            "PASA_BAJO": "0014",
            "PASA_ALTO": "0051",
            "BATERIA": 12.47
        },
        {
            "FECHA": "2025-08-13",
            "TIEMPO": "12:28:00",
            "LATITUD": -0.212142,
            "LONGITUD": -78.491418,
            "ALTURA": 2831.1,
            "PASA_BANDA": "0012",
            "PASA_BAJO": "0019",
            "PASA_ALTO": "0051",
            "BATERIA": 12.46
        },
        {
            "FECHA": "2025-08-13",
            "TIEMPO": "12:29:00",
            "LATITUD": -0.212142,
            "LONGITUD": -78.491447,
            "ALTURA": 2827.0,
            "PASA_BANDA": "0013",
            "PASA_BAJO": "0012",
            "PASA_ALTO": "0052",
            "BATERIA": 12.46
        },
        {
            "FECHA": "2025-08-13",
            "TIEMPO": "12:30:00",
            "LATITUD": -0.212138,
            "LONGITUD": -78.491476,
            "ALTURA": 2816.9,
            "PASA_BANDA": "0012",
            "PASA_BAJO": "0020",
            "PASA_ALTO": "0053",
            "BATERIA": 12.46
        },
        {
            "FECHA": "2025-08-13",
            "TIEMPO": "12:31:00",
            "LATITUD": -0.212142,
            "LONGITUD": -78.491482,
            "ALTURA": 2813.7,
            "PASA_BANDA": "0015",
            "PASA_BAJO": "0012",
            "PASA_ALTO": "0056",
            "BATERIA": 12.46
        },
        {
            "FECHA": "2025-08-13",
            "TIEMPO": "12:32:00",
            "LATITUD": -0.212115,
            "LONGITUD": -78.491495,
            "ALTURA": 2817.3,
            "PASA_BANDA": "0016",
            "PASA_BAJO": "0009",
            "PASA_ALTO": "0054",
            "BATERIA": 12.46
        },
        {
            "FECHA": "2025-08-13",
            "TIEMPO": "12:33:00",
            "LATITUD": -0.212086,
            "LONGITUD": -78.491465,
            "ALTURA": 2827.9,
            "PASA_BANDA": "0015",
            "PASA_BAJO": "0009",
            "PASA_ALTO": "0053",
            "BATERIA": 12.46
        },
        {
            "FECHA": "2025-08-13",
            "TIEMPO": "12:34:00",
            "LATITUD": -0.212045,
            "LONGITUD": -78.491445,
            "ALTURA": 2842.9,
            "PASA_BANDA": "0015",
            "PASA_BAJO": "0012",
            "PASA_ALTO": "0053",
            "BATERIA": 12.46
        },
        {
            "FECHA": "2025-08-13",
            "TIEMPO": "12:35:00",
            "LATITUD": -0.212068,
            "LONGITUD": -78.491456,
            "ALTURA": 2833.8,
            "PASA_BANDA": "0015",
            "PASA_BAJO": "0012",
            "PASA_ALTO": "0051",
            "BATERIA": 12.46
        },
        {
            "FECHA": "2025-08-13",
            "TIEMPO": "12:36:00",
            "LATITUD": -0.212054,
            "LONGITUD": -78.491457,
            "ALTURA": 2836.0,
            "PASA_BANDA": "0008",
            "PASA_BAJO": "0010",
            "PASA_ALTO": "0051",
            "BATERIA": 12.46
        },
        {
            "FECHA": "2025-08-13",
            "TIEMPO": "12:37:00",
            "LATITUD": -0.212057,
            "LONGITUD": -78.491459,
            "ALTURA": 2836.1,
            "PASA_BANDA": "0015",
            "PASA_BAJO": "0008",
            "PASA_ALTO": "0051",
            "BATERIA": 12.46
        },
        {
            "FECHA": "2025-08-13",
            "TIEMPO": "12:38:00",
            "LATITUD": -0.212079,
            "LONGITUD": -78.491473,
            "ALTURA": 2834.0,
            "PASA_BANDA": "0013",
            "PASA_BAJO": "0009",
            "PASA_ALTO": "0055",
            "BATERIA": 12.46
        },
        {
            "FECHA": "2025-08-13",
            "TIEMPO": "12:39:00",
            "LATITUD": -0.212053,
            "LONGITUD": -78.491451,
            "ALTURA": 2844.1,
            "PASA_BANDA": "0016",
            "PASA_BAJO": "0008",
            "PASA_ALTO": "0056",
            "BATERIA": 12.46
        },
        {
            "FECHA": "2025-08-13",
            "TIEMPO": "12:40:00",
            "LATITUD": -0.212063,
            "LONGITUD": -78.491435,
            "ALTURA": 2846.1,
            "PASA_BANDA": "0016",
            "PASA_BAJO": "0008",
            "PASA_ALTO": "0056",
            "BATERIA": 12.46
        },
        {
            "FECHA": "2025-08-13",
            "TIEMPO": "12:41:00",
            "LATITUD": -0.212067,
            "LONGITUD": -78.491442,
            "ALTURA": 2840.6,
            "PASA_BANDA": "0016",
            "PASA_BAJO": "0012",
            "PASA_ALTO": "0056",
            "BATERIA": 12.46
        },
        {
            "FECHA": "2025-08-13",
            "TIEMPO": "12:42:00",
            "LATITUD": -0.212043,
            "LONGITUD": -78.491451,
            "ALTURA": 2838.7,
            "PASA_BANDA": "0016",
            "PASA_BAJO": "0016",
            "PASA_ALTO": "0056",
            "BATERIA": 12.46
        },
        {
            "FECHA": "2025-08-13",
            "TIEMPO": "12:43:00",
            "LATITUD": -0.212043,
            "LONGITUD": -78.491451,
            "ALTURA": 2837.6,
            "PASA_BANDA": "0009",
            "PASA_BAJO": "0011",
            "PASA_ALTO": "0056",
            "BATERIA": 12.46
        },
        {
            "FECHA": "2025-08-13",
            "TIEMPO": "12:44:00",
            "LATITUD": -0.212036,
            "LONGITUD": -78.491461,
            "ALTURA": 2840.3,
            "PASA_BANDA": "0009",
            "PASA_BAJO": "0012",
            "PASA_ALTO": "0056",
            "BATERIA": 12.46
        },
        {
            "FECHA": "2025-08-13",
            "TIEMPO": "12:45:00",
            "LATITUD": -0.212033,
            "LONGITUD": -78.49145,
            "ALTURA": 2840.5,
            "PASA_BANDA": "0015",
            "PASA_BAJO": "0017",
            "PASA_ALTO": "0056",
            "BATERIA": 12.46
        },
        {
            "FECHA": "2025-08-13",
            "TIEMPO": "12:46:00",
            "LATITUD": -0.212055,
            "LONGITUD": -78.491438,
            "ALTURA": 2833.0,
            "PASA_BANDA": "0008",
            "PASA_BAJO": "0013",
            "PASA_ALTO": "0056",
            "BATERIA": 12.46
        },
        {
            "FECHA": "2025-08-13",
            "TIEMPO": "12:47:00",
            "LATITUD": -0.212064,
            "LONGITUD": -78.491422,
            "ALTURA": 2830.9,
            "PASA_BANDA": "0008",
            "PASA_BAJO": "0019",
            "PASA_ALTO": "0055",
            "BATERIA": 12.47
        },
        {
            "FECHA": "2025-08-13",
            "TIEMPO": "12:48:00",
            "LATITUD": -0.212033,
            "LONGITUD": -78.491409,
            "ALTURA": 2834.5,
            "PASA_BANDA": "0009",
            "PASA_BAJO": "0014",
            "PASA_ALTO": "0053",
            "BATERIA": 12.47
        },
        {
            "FECHA": "2025-08-13",
            "TIEMPO": "12:49:00",
            "LATITUD": -0.212036,
            "LONGITUD": -78.491404,
            "ALTURA": 2844.6,
            "PASA_BANDA": "0012",
            "PASA_BAJO": "0021",
            "PASA_ALTO": "0051",
            "BATERIA": 12.46
        },
        {
            "FECHA": "2025-08-13",
            "TIEMPO": "12:50:00",
            "LATITUD": -0.212034,
            "LONGITUD": -78.491404,
            "ALTURA": 2845.4,
            "PASA_BANDA": "0008",
            "PASA_BAJO": "0015",
            "PASA_ALTO": "0051",
            "BATERIA": 12.46
        },
        {
            "FECHA": "2025-08-13",
            "TIEMPO": "12:51:00",
            "LATITUD": -0.212025,
            "LONGITUD": -78.491395,
            "ALTURA": 2845.2,
            "PASA_BANDA": "0013",
            "PASA_BAJO": "0010",
            "PASA_ALTO": "0051",
            "BATERIA": 12.46
        },
        {
            "FECHA": "2025-08-13",
            "TIEMPO": "12:52:00",
            "LATITUD": -0.212035,
            "LONGITUD": -78.491406,
            "ALTURA": 2839.2,
            "PASA_BANDA": "0015",
            "PASA_BAJO": "0008",
            "PASA_ALTO": "0051",
            "BATERIA": 12.46
        },
        {
            "FECHA": "2025-08-13",
            "TIEMPO": "12:53:00",
            "LATITUD": -0.212056,
            "LONGITUD": -78.491406,
            "ALTURA": 2836.8,
            "PASA_BANDA": "0017",
            "PASA_BAJO": "0008",
            "PASA_ALTO": "0056",
            "BATERIA": 12.46
        },
        {
            "FECHA": "2025-08-13",
            "TIEMPO": "12:54:00",
            "LATITUD": -0.212035,
            "LONGITUD": -78.491409,
            "ALTURA": 2839.4,
            "PASA_BANDA": "0016",
            "PASA_BAJO": "0008",
            "PASA_ALTO": "0053",
            "BATERIA": 12.47
        },
        {
            "FECHA": "2025-08-13",
            "TIEMPO": "12:55:00",
            "LATITUD": -0.212025,
            "LONGITUD": -78.491394,
            "ALTURA": 2852.2,
            "PASA_BANDA": "0008",
            "PASA_BAJO": "0012",
            "PASA_ALTO": "0056",
            "BATERIA": 12.47
        },
        {
            "FECHA": "2025-08-13",
            "TIEMPO": "12:56:00",
            "LATITUD": -0.212025,
            "LONGITUD": -78.491393,
            "ALTURA": 2852.3,
            "PASA_BANDA": "0015",
            "PASA_BAJO": "0012",
            "PASA_ALTO": "0056",
            "BATERIA": 12.46
        },
        {
            "FECHA": "2025-08-13",
            "TIEMPO": "12:57:00",
            "LATITUD": -0.212039,
            "LONGITUD": -78.491402,
            "ALTURA": 2843.8,
            "PASA_BANDA": "0014",
            "PASA_BAJO": "0009",
            "PASA_ALTO": "0056",
            "BATERIA": 12.46
        },
        {
            "FECHA": "2025-08-13",
            "TIEMPO": "12:58:00",
            "LATITUD": -0.212011,
            "LONGITUD": -78.491404,
            "ALTURA": 2847.9,
            "PASA_BANDA": "0015",
            "PASA_BAJO": "0030",
            "PASA_ALTO": "0058",
            "BATERIA": 12.46
        },
        {
            "FECHA": "2025-08-13",
            "TIEMPO": "12:59:00",
            "LATITUD": -0.212059,
            "LONGITUD": -78.491422,
            "ALTURA": 2833.7,
            "PASA_BANDA": "0014",
            "PASA_BAJO": "0061",
            "PASA_ALTO": "0062",
            "BATERIA": 12.47
        }
    ]
}